feClient/__init__.py
feClient/__main__.py
feClient/client.py
feClient/py.typed
python_feclient-0.2.0.data/scripts/fexplorer-cli
python_feclient-0.2.0.dist-info/LICENSE.md
python_feclient-0.2.0.dist-info/METADATA
python_feclient-0.2.0.dist-info/WHEEL
python_feclient-0.2.0.dist-info/top_level.txt
python_feclient-0.2.0.dist-info/RECORD
